{
  "metadata": {
    "caption": "Water level as on 26.04.2025 at 7.00 AM",
    "source": "https://dams.kseb.in/?p=5261",
    "scraped_at": "2025-04-26T05:35:09.401Z"
  },
  "data": [
    {
      "Sl. No.": "1",
      "Name of Dam / Reservoir": "IDUKKI",
      "District": "IDK",
      "MWL (metre)": "2408.5 ft",
      "FRL (metre)": "2403 ft",
      "Spillway Crest Level (metre)": "2373 ft",
      "Live Storage at FRL (MCM)": "1459.49",
      "Rule level(metre)": "2403.00 ft",
      "Blue level(metre)": "2395.00",
      "Orange level(metre)": "2401.00",
      "Red Level(metre)": "2402.00",
      "Today&#8217;s Water level (metre)": "2343.40",
      "Today&#8217;s Live Storage(MCM)": "588.242",
      "% Storage w.r.t Live Storage at FRL": "40.30%",
      "Same day previous year Water level (metre)": "2339.70",
      "Same day previous year Live Storage&nbsp; (MCM)": "543.284",
      "&nbsp;Inflow (cumecs)": "8.09",
      "Power House Discharge(cumecs)": "79.71",
      "Spillway release (cumecs)": "0.00",
      "Total Outflow (cumecs)": "79.71",
      "Rainfall (mm)": "0.00",
      "Remarks": "&nbsp;"
    },
    {
      "Sl. No.": "2",
      "Name of Dam / Reservoir": "IDAMALAYAR",
      "District": "EKM",
      "MWL (metre)": "171.00",
      "FRL (metre)": "169.00",
      "Spillway Crest Level (metre)": "161.00",
      "Live Storage at FRL (MCM)": "1017.80",
      "Rule level(metre)": "169.00",
      "Blue level(metre)": "167.50",
      "Orange level(metre)": "168.00",
      "Red Level(metre)": "168.50",
      "Today&#8217;s Water level (metre)": "141.71",
      "Today&#8217;s Live Storage(MCM)": "342.288",
      "% Storage w.r.t Live Storage at FRL": "33.63%",
      "Same day previous year Water level (metre)": "142.97",
      "Same day previous year Live Storage&nbsp; (MCM)": "366.670",
      "&nbsp;Inflow (cumecs)": "6.71",
      "Power House Discharge(cumecs)": "64.29",
      "Spillway release (cumecs)": "0.00",
      "Total Outflow (cumecs)": "64.29",
      "Rainfall (mm)": "29.40",
      "Remarks": "&nbsp;"
    },
    {
      "Sl. No.": "3",
      "Name of Dam / Reservoir": "KAKKI (ANATHODE )",
      "District": "PTTA",
      "MWL (metre)": "982.160",
      "FRL (metre)": "981.46",
      "Spillway Crest Level (metre)": "975.360",
      "Live Storage at FRL (MCM)": "446.51",
      "Rule level(metre)": "981.46",
      "Blue level(metre)": "979.46",
      "Orange level(metre)": "980.46",
      "Red Level(metre)": "980.96",
      "Today&#8217;s Water level (metre)": "961.10",
      "Today&#8217;s Live Storage(MCM)": "191.950",
      "% Storage w.r.t Live Storage at FRL": "42.99%",
      "Same day previous year Water level (metre)": "957.56",
      "Same day previous year Live Storage&nbsp; (MCM)": "162.380",
      "&nbsp;Inflow (cumecs)": "9.14",
      "Power House Discharge(cumecs)": "43.63",
      "Spillway release (cumecs)": "0.00",
      "Total Outflow (cumecs)": "43.63",
      "Rainfall (mm)": "0.00",
      "Remarks": "&nbsp;"
    },
    {
      "Sl. No.": "4",
      "Name of Dam / Reservoir": "BANASURASAGAR(K A SCHEME)",
      "District": "WND",
      "MWL (metre)": "775.600",
      "FRL (metre)": "775.60",
      "Spillway Crest Level (metre)": "767.000",
      "Live Storage at FRL (MCM)": "201.00",
      "Rule level(metre)": "775.60",
      "Blue level(metre)": "774.10",
      "Orange level(metre)": "774.60",
      "Red Level(metre)": "775.10",
      "Today&#8217;s Water level (metre)": "760.60",
      "Today&#8217;s Live Storage(MCM)": "48.950",
      "% Storage w.r.t Live Storage at FRL": "24.35%",
      "Same day previous year Water level (metre)": "760.05",
      "Same day previous year Live Storage&nbsp; (MCM)": "44.950",
      "&nbsp;Inflow (cumecs)": "0.00",
      "Power House Discharge(cumecs)": "8.91",
      "Spillway release (cumecs)": "0.00",
      "Total Outflow (cumecs)": "8.91",
      "Rainfall (mm)": "6.00",
      "Remarks": "Tunnel Discharge -0.77 Mcm"
    },
    {
      "Sl. No.": "5",
      "Name of Dam / Reservoir": "SHOLAYAR",
      "District": "TSR",
      "MWL (metre)": "2663 ft",
      "FRL (metre)": "2663 ft",
      "Spillway Crest Level (metre)": "2642 ft",
      "Live Storage at FRL (MCM)": "149.09",
      "Rule level(metre)": "&nbsp;",
      "Blue level(metre)": "2658.00",
      "Orange level(metre)": "2660.00",
      "Red Level(metre)": "2661.00",
      "Today&#8217;s Water level (metre)": "2619.00ft",
      "Today&#8217;s Live Storage(MCM)": "55.470",
      "% Storage w.r.t Live Storage at FRL": "37.21%",
      "Same day previous year Water level (metre)": "2605.60ft",
      "Same day previous year Live Storage&nbsp; (MCM)": "36.990",
      "&nbsp;Inflow (cumecs)": "3.64",
      "Power House Discharge(cumecs)": "17.80",
      "Spillway release (cumecs)": "0.00",
      "Total Outflow (cumecs)": "17.80",
      "Rainfall (mm)": "0.00",
      "Remarks": "&nbsp;"
    },
    {
      "Sl. No.": "6",
      "Name of Dam / Reservoir": "MADUPETTY",
      "District": "IDK",
      "MWL (metre)": "1599.59",
      "FRL (metre)": "1599.59",
      "Spillway Crest Level (metre)": "1594.71",
      "Live Storage at FRL (MCM)": "54.77",
      "Rule level(metre)": "&nbsp;",
      "Blue level(metre)": "1596.00",
      "Orange level(metre)": "1597.00",
      "Red Level(metre)": "1598.00",
      "Today&#8217;s Water level (metre)": "1586.40",
      "Today&#8217;s Live Storage(MCM)": "24.140",
      "% Storage w.r.t Live Storage at FRL": "44.08%",
      "Same day previous year Water level (metre)": "1589.70",
      "Same day previous year Live Storage&nbsp; (MCM)": "30.740",
      "&nbsp;Inflow (cumecs)": "0.00",
      "Power House Discharge(cumecs)": "3.68",
      "Spillway release (cumecs)": "0.00",
      "Total Outflow (cumecs)": "3.68",
      "Rainfall (mm)": "16.00",
      "Remarks": "Sluice Discharge -0.2691"
    },
    {
      "Sl. No.": "7",
      "Name of Dam / Reservoir": "ANAYIRANKAL",
      "District": "IDK",
      "MWL (metre)": "1210.070",
      "FRL (metre)": "1207.02",
      "Spillway Crest Level (metre)": "1207.02",
      "Live Storage at FRL (MCM)": "49.83",
      "Rule level(metre)": "&nbsp;",
      "Blue level(metre)": "1205.02",
      "Orange level(metre)": "1206.02",
      "Red Level(metre)": "1207.02",
      "Today&#8217;s Water level (metre)": "1198.92",
      "Today&#8217;s Live Storage(MCM)": "19.473",
      "% Storage w.r.t Live Storage at FRL": "39.08%",
      "Same day previous year Water level (metre)": "1197.58",
      "Same day previous year Live Storage&nbsp; (MCM)": "15.2056",
      "&nbsp;Inflow (cumecs)": "3.83",
      "Power House Discharge(cumecs)": "0.00",
      "Spillway release (cumecs)": "0.00",
      "Total Outflow (cumecs)": "0.00",
      "Rainfall (mm)": "0.00",
      "Remarks": "Sluice Discharge -1.00 MCM"
    },
    {
      "Sl. No.": "8",
      "Name of Dam / Reservoir": "PONMUDI",
      "District": "IDK",
      "MWL (metre)": "708.660",
      "FRL (metre)": "707.750",
      "Spillway Crest Level (metre)": "701.350",
      "Live Storage at FRL (MCM)": "47.40",
      "Rule level(metre)": "&nbsp;",
      "Blue level(metre)": "704.50",
      "Orange level(metre)": "705.50",
      "Red Level(metre)": "706.50",
      "Today&#8217;s Water level (metre)": "700.90",
      "Today&#8217;s Live Storage(MCM)": "31.967",
      "% Storage w.r.t Live Storage at FRL": "67.44%",
      "Same day previous year Water level (metre)": "693.65",
      "Same day previous year Live Storage&nbsp; (MCM)": "19.7572",
      "&nbsp;Inflow (cumecs)": "7.91",
      "Power House Discharge(cumecs)": "11.37",
      "Spillway release (cumecs)": "0.00",
      "Total Outflow (cumecs)": "11.37",
      "Rainfall (mm)": "0.00",
      "Remarks": "&nbsp;"
    },
    {
      "Sl. No.": "9",
      "Name of Dam / Reservoir": "KUTTIYADI(KAKKAYAM)",
      "District": "KKD",
      "MWL (metre)": "758.040",
      "FRL (metre)": "758.040",
      "Spillway Crest Level (metre)": "751.640",
      "Live Storage at FRL (MCM)": "33.98",
      "Rule level(metre)": "&nbsp;",
      "Blue level(metre)": "755.50",
      "Orange level(metre)": "756.50",
      "Red Level(metre)": "757.50",
      "Today&#8217;s Water level (metre)": "750.630",
      "Today&#8217;s Live Storage(MCM)": "17.050",
      "% Storage w.r.t Live Storage at FRL": "50.18%",
      "Same day previous year Water level (metre)": "749.78",
      "Same day previous year Live Storage&nbsp; (MCM)": "15.340",
      "&nbsp;Inflow (cumecs)": "9.86",
      "Power House Discharge(cumecs)": "8.46",
      "Spillway release (cumecs)": "0.00",
      "Total Outflow (cumecs)": "8.46",
      "Rainfall (mm)": "0.00",
      "Remarks": "&nbsp;"
    },
    {
      "Sl. No.": "10",
      "Name of Dam / Reservoir": "PAMBA",
      "District": "PTTA",
      "MWL (metre)": "986.330",
      "FRL (metre)": "986.330",
      "Spillway Crest Level (metre)": "981.460",
      "Live Storage at FRL (MCM)": "31.15",
      "Rule level(metre)": "&nbsp;",
      "Blue level(metre)": "982.00",
      "Orange level(metre)": "983.50",
      "Red Level(metre)": "984.50",
      "Today&#8217;s Water level (metre)": "963.55",
      "Today&#8217;s Live Storage(MCM)": "0.28",
      "% Storage w.r.t Live Storage at FRL": "0.90%",
      "Same day previous year Water level (metre)": "962.75",
      "Same day previous year Live Storage&nbsp; (MCM)": "0.00",
      "&nbsp;Inflow (cumecs)": "1.33",
      "Power House Discharge(cumecs)": "0.00",
      "Spillway release (cumecs)": "0.00",
      "Total Outflow (cumecs)": "0.00",
      "Rainfall (mm)": "18.00",
      "Remarks": "&nbsp;"
    },
    {
      "Sl. No.": "11",
      "Name of Dam / Reservoir": "PORINGALKUTHU",
      "District": "TSR",
      "MWL (metre)": "423.980",
      "FRL (metre)": "423.980",
      "Spillway Crest Level (metre)": "419.410",
      "Live Storage at FRL (MCM)": "30.30",
      "Rule level(metre)": "&nbsp;",
      "Blue level(metre)": "421.00",
      "Orange level(metre)": "422.00",
      "Red Level(metre)": "423.00",
      "Today&#8217;s Water level (metre)": "413.10",
      "Today&#8217;s Live Storage(MCM)": "6.60",
      "% Storage w.r.t Live Storage at FRL": "21.78%",
      "Same day previous year Water level (metre)": "414.70",
      "Same day previous year Live Storage&nbsp; (MCM)": "9.00",
      "&nbsp;Inflow (cumecs)": "0.00",
      "Power House Discharge(cumecs)": "18.20",
      "Spillway release (cumecs)": "0.00",
      "Total Outflow (cumecs)": "18.20",
      "Rainfall (mm)": "1.40",
      "Remarks": "&nbsp;"
    },
    {
      "Sl. No.": "12",
      "Name of Dam / Reservoir": "KUNDALA",
      "District": "IDK",
      "MWL (metre)": "1759.30",
      "FRL (metre)": "1758.690",
      "Spillway Crest Level (metre)": "&nbsp;",
      "Live Storage at FRL (MCM)": "7.65",
      "Rule level(metre)": "&nbsp;",
      "Blue level(metre)": "1755.00",
      "Orange level(metre)": "1756.00",
      "Red Level(metre)": "1757.00",
      "Today&#8217;s Water level (metre)": "1757.75",
      "Today&#8217;s Live Storage(MCM)": "6.725",
      "% Storage w.r.t Live Storage at FRL": "87.91%",
      "Same day previous year Water level (metre)": "1758.10",
      "Same day previous year Live Storage&nbsp; (MCM)": "6.970",
      "&nbsp;Inflow (cumecs)": "0.68",
      "Power House Discharge(cumecs)": "0.00",
      "Spillway release (cumecs)": "0.68",
      "Total Outflow (cumecs)": "0.68",
      "Rainfall (mm)": "7.00",
      "Remarks": "&nbsp;"
    },
    {
      "Sl. No.": "13",
      "Name of Dam / Reservoir": "KALLARKUTTY",
      "District": "IDK",
      "MWL (metre)": "456.900",
      "FRL (metre)": "456.590",
      "Spillway Crest Level (metre)": "450.200",
      "Live Storage at FRL (MCM)": "6.43",
      "Rule level(metre)": "&nbsp;",
      "Blue level(metre)": "&nbsp;",
      "Orange level(metre)": "&nbsp;",
      "Red Level(metre)": "455.00",
      "Today&#8217;s Water level (metre)": "453.40",
      "Today&#8217;s Live Storage(MCM)": "4.443",
      "% Storage w.r.t Live Storage at FRL": "69.10%",
      "Same day previous year Water level (metre)": "453.90",
      "Same day previous year Live Storage&nbsp; (MCM)": "4.760",
      "&nbsp;Inflow (cumecs)": "12.63",
      "Power House Discharge(cumecs)": "14.09",
      "Spillway release (cumecs)": "0.00",
      "Total Outflow (cumecs)": "14.09",
      "Rainfall (mm)": "0.00",
      "Remarks": "&nbsp;"
    },
    {
      "Sl. No.": "14",
      "Name of Dam / Reservoir": "ERATTAYAR",
      "District": "IDK",
      "MWL (metre)": "754.380",
      "FRL (metre)": "754.380",
      "Spillway Crest Level (metre)": "748.280",
      "Live Storage at FRL (MCM)": "5.29",
      "Rule level(metre)": "&nbsp;",
      "Blue level(metre)": "&nbsp;",
      "Orange level(metre)": "&nbsp;",
      "Red Level(metre)": "748.28",
      "Today&#8217;s Water level (metre)": "746.20",
      "Today&#8217;s Live Storage(MCM)": "0.7297",
      "% Storage w.r.t Live Storage at FRL": "13.79%",
      "Same day previous year Water level (metre)": "746.30",
      "Same day previous year Live Storage&nbsp; (MCM)": "&nbsp;",
      "&nbsp;Inflow (cumecs)": "&nbsp;",
      "Power House Discharge(cumecs)": "&nbsp;",
      "Spillway release (cumecs)": "&nbsp;",
      "Total Outflow (cumecs)": "&nbsp;",
      "Rainfall (mm)": "&nbsp;",
      "Remarks": "&nbsp;"
    },
    {
      "Sl. No.": "15",
      "Name of Dam / Reservoir": "LOWER PERIYAR&nbsp;",
      "District": "IDK",
      "MWL (metre)": "256.00",
      "FRL (metre)": "253.00",
      "Spillway Crest Level (metre)": "237.74",
      "Live Storage at FRL (MCM)": "4.55",
      "Rule level(metre)": "&nbsp;",
      "Blue level(metre)": "&nbsp;",
      "Orange level(metre)": "&nbsp;",
      "Red Level(metre)": "252.00",
      "Today&#8217;s Water level (metre)": "249.60",
      "Today&#8217;s Live Storage(MCM)": "3.134",
      "% Storage w.r.t Live Storage at FRL": "68.88%",
      "Same day previous year Water level (metre)": "250.60",
      "Same day previous year Live Storage&nbsp; (MCM)": "3.536",
      "&nbsp;Inflow (cumecs)": "13.08",
      "Power House Discharge(cumecs)": "14.43",
      "Spillway release (cumecs)": "0.00",
      "Total Outflow (cumecs)": "14.43",
      "Rainfall (mm)": "0.00",
      "Remarks": "&nbsp;"
    },
    {
      "Sl. No.": "16",
      "Name of Dam / Reservoir": "MOOZHIYAR",
      "District": "PTTA",
      "MWL (metre)": "192.940",
      "FRL (metre)": "192.630",
      "Spillway Crest Level (metre)": "186.530",
      "Live Storage at FRL (MCM)": "1.16",
      "Rule level(metre)": "&nbsp;",
      "Blue level(metre)": "&nbsp;",
      "Orange level(metre)": "&nbsp;",
      "Red Level(metre)": "190.00",
      "Today&#8217;s Water level (metre)": "186.10",
      "Today&#8217;s Live Storage(MCM)": "0.375",
      "% Storage w.r.t Live Storage at FRL": "32.33%",
      "Same day previous year Water level (metre)": "188.50",
      "Same day previous year Live Storage&nbsp; (MCM)": "0.623",
      "&nbsp;Inflow (cumecs)": "30.91",
      "Power House Discharge(cumecs)": "32.10",
      "Spillway release (cumecs)": "0.00",
      "Total Outflow (cumecs)": "32.10",
      "Rainfall (mm)": "69.00",
      "Remarks": "&nbsp;"
    },
    {
      "Sl. No.": "17",
      "Name of Dam / Reservoir": "KALLAR",
      "District": "IDK",
      "MWL (metre)": "824.480",
      "FRL (metre)": "824.480",
      "Spillway Crest Level (metre)": "818.380",
      "Live Storage at FRL (MCM)": "0.76",
      "Rule level(metre)": "&nbsp;",
      "Blue level(metre)": "&nbsp;",
      "Orange level(metre)": "&nbsp;",
      "Red Level(metre)": "823.50",
      "Today&#8217;s Water level (metre)": "819.70",
      "Today&#8217;s Live Storage(MCM)": "0.1684",
      "% Storage w.r.t Live Storage at FRL": "22.07%",
      "Same day previous year Water level (metre)": "819.40",
      "Same day previous year Live Storage&nbsp; (MCM)": "&nbsp;",
      "&nbsp;Inflow (cumecs)": "&nbsp;",
      "Power House Discharge(cumecs)": "&nbsp;",
      "Spillway release (cumecs)": "&nbsp;",
      "Total Outflow (cumecs)": "&nbsp;",
      "Rainfall (mm)": "&nbsp;",
      "Remarks": "&nbsp;"
    },
    {
      "Sl. No.": "18",
      "Name of Dam / Reservoir": "SENGULAM (PUMPING STORAGE DAM)",
      "District": "IDK",
      "MWL (metre)": "849.49",
      "FRL (metre)": "847.640",
      "Spillway Crest Level (metre)": "847.64",
      "Live Storage at FRL (MCM)": "0.39",
      "Rule level(metre)": "&nbsp;",
      "Blue level(metre)": "&nbsp;",
      "Orange level(metre)": "&nbsp;",
      "Red Level(metre)": "&nbsp;",
      "Today&#8217;s Water level (metre)": "846.60",
      "Today&#8217;s Live Storage(MCM)": "0.142",
      "% Storage w.r.t Live Storage at FRL": "36.41%",
      "Same day previous year Water level (metre)": "846.70",
      "Same day previous year Live Storage&nbsp; (MCM)": "0.165",
      "&nbsp;Inflow (cumecs)": "6.80",
      "Power House Discharge(cumecs)": "7.62",
      "Spillway release (cumecs)": "0.00",
      "Total Outflow (cumecs)": "7.62",
      "Rainfall (mm)": "0.00",
      "Remarks": "&nbsp;"
    }
  ]
}